telicent_lbapi/__init__.py
telicent_lbapi/context.py
telicent_lbapi/decorators.py
telicent_lbapi/rest_service.py
telicent_lbapi/sbom.json
telicent_lbapi/api/__init__.py
telicent_lbapi/api/v1/__init__.py
telicent_lbapi/api/v1/endpoints/__init__.py
telicent_lbapi/api/v1/endpoints/ingest.py
telicent_lbapi/core/__init__.py
telicent_lbapi/core/api_config/__init__.py
telicent_lbapi/core/api_config/config.py
telicent_lbapi/core/api_config/log_config.py
telicent_lbapi/core/middleware/__init__.py
telicent_lbapi/core/middleware/context_middleware.py
telicent_lbapi/services/__init__.py
telicent_lbapi/services/label_builder_service.py
telicent_lbapi/utils/__init__.py
telicent_lbapi/utils/cache.py
telicent_lbapi/utils/helpers.py
telicent_label_builder_service-0.1.5.dist-info/LICENSE
telicent_label_builder_service-0.1.5.dist-info/METADATA
telicent_label_builder_service-0.1.5.dist-info/NOTICE
telicent_label_builder_service-0.1.5.dist-info/WHEEL
telicent_label_builder_service-0.1.5.dist-info/top_level.txt
telicent_label_builder_service-0.1.5.dist-info/RECORD
