Metadata-Version: 2.1
Name: telicent-label-builder-service
Version: 0.1.5
Summary: A helper package to create security labels from data header
Author-email: Telicent Ltd <opensource@telicent.io>
License: Apache License
Project-URL: Repository, https://github.com/telicent-oss/label-builder-service
Classifier: Programming Language :: Python :: 3.10
Classifier: Programming Language :: Python :: 3.11
Classifier: Programming Language :: Python :: 3.12
Classifier: Programming Language :: Python :: 3 :: Only
Classifier: Topic :: Software Development
Classifier: Typing :: Typed
Classifier: Operating System :: Microsoft :: Windows
Classifier: Operating System :: POSIX
Classifier: Operating System :: Unix
Classifier: Operating System :: MacOS
Requires-Python: >=3.10
License-File: LICENSE
License-File: NOTICE
Requires-Dist: fastapi ==0.115.2
Requires-Dist: starlette >=0.40.0
Requires-Dist: httpx ==0.27.2
Requires-Dist: telicent-lib >=2.0.5
Requires-Dist: uvicorn ==0.30.1
Requires-Dist: python-dotenv ~=1.0.1
Requires-Dist: python-json-logger ==2.0.7
Requires-Dist: asgi-correlation-id ==4.3.1
Requires-Dist: starlette-context ==0.3.6
Requires-Dist: cachetools ==5.4.0
Provides-Extra: dev
Requires-Dist: pre-commit ==3.5.0 ; extra == 'dev'
Requires-Dist: ruff ==0.1.5 ; extra == 'dev'
Requires-Dist: types-pytz ==2024.1.0.20240417 ; extra == 'dev'
Requires-Dist: urllib3 ==2.2.2 ; extra == 'dev'
Requires-Dist: types-requests ==2.32.0.20240622 ; extra == 'dev'
Requires-Dist: mypy ==1.7.0 ; extra == 'dev'
Requires-Dist: cyclonedx-bom ==4.4.3 ; extra == 'dev'
Requires-Dist: types-cachetools ==5.4.0.20240717 ; extra == 'dev'
Provides-Extra: test
Requires-Dist: telicent-label-builder ==0.1.1 ; extra == 'test'
Requires-Dist: pytest ==8.2.2 ; extra == 'test'
Requires-Dist: pytest-asyncio ==0.23.7 ; extra == 'test'
